xuexitong_fileloads/__init__.py
xuexitong_fileloads/config.json
xuexitong_fileloads/config.py
xuexitong_fileloads/load_xuexitong.py
xuexitong_fileloads/login.py
xuexitong_fileloads/test.py
xuexitong_fileloads/utils.py
xuexitong_fileloads/图片链接下载.py
xuexitong_fileloads-0.1.6.dist-info/LICENSE
xuexitong_fileloads-0.1.6.dist-info/METADATA
xuexitong_fileloads-0.1.6.dist-info/WHEEL
xuexitong_fileloads-0.1.6.dist-info/RECORD
